digit_base_conversions/__init__.py
digit_base_conversions-0.2.dist-info/METADATA
digit_base_conversions-0.2.dist-info/WHEEL
digit_base_conversions-0.2.dist-info/top_level.txt
digit_base_conversions-0.2.dist-info/RECORD
